<?xml version="1.0" encoding="utf-8"?><soap:Envelope xmlns:soap="http://schemas.xmlsoap.org/soap/envelope/" xmlns:xsi="http://www.w3.org/2001/XMLSchema-instance" xmlns:xsd="http://www.w3.org/2001/XMLSchema"><soap:Body><CautareDosareResponse xmlns="portalquery.just.ro"><CautareDosareResult><Dosar><parti><DosarParte><nume>BOLOHAN VALENTINA LA CAB AV PĂUN RODICA</nume><calitateParte>Reclamant</calitateParte></DosarParte><DosarParte><nume>LUPU PETRU</nume><calitateParte>Pârât</calitateParte></DosarParte></parti><sedinte><DosarSedinta><complet>C13</complet><data>2018-03-30T00:00:00</data><ora>08:30</ora><solutie>Admite cererea</solutie><solutieSumar>Admite cererea având ca obiect exercitarea autorităţii părinteşti formulată de reclamanta pârâtă Bolohan Valentina în contradictoriu cu pârâtul reclamant Lupu Petru.
	Admite în parte cererea reconvenţională.
	Dispune ca exercitarea autorităţii părinteşti faţă de minorul Lupu Matei, născut la data de 02.04.2015 să se facă în mod exclusiv de către reclamantă.
	Stabileşte  locuinţa minorului la domiciliul reclamantei.
	Obligă pârâtul să plătească o pensie de întreţinere în favoarea minorului în cuantum de 1000 lei, de la data introducerii acţiunii, 01.03.2017 şi până la majoratul minorului.
	Încuviinţează cererea pârâtului reclamant de stabilire legături personale cu minorul Lupu Matei, în sensul că stabileşte un program de vizită, la domiciliul minorului, între orele 16,00-20,00, ori de câte ori va putea pârâtul să se deplaseze la locuinţa minorului şi la domiciliul său, între orele 12,00-20,00 ori de câte ori minorul se va afla în România.
	Cu drept de apel, ce se depune la Judecătoria Botoşani, în termen de 30 de zile de la comunicare.
	Pronunţată în şedinţă publică, azi, 30.03.2018.
</solutieSumar><dataPronuntare>2018-03-30T00:00:00</dataPronuntare><documentSedinta>Hotarare</documentSedinta><numarDocument>1530/2018</numarDocument><dataDocument>2018-03-30T00:00:00</dataDocument></DosarSedinta><DosarSedinta><complet>C13</complet><data>2018-03-19T00:00:00</data><ora>08:30</ora><solutie>Amână pronunţarea</solutie><solutieSumar>Amână pronunţarea cauzei la data de 30.03.2018.
	Pronunţată în şedinţa publică, azi,  19.03.2018.
</solutieSumar><dataPronuntare>2018-03-19T00:00:00</dataPronuntare><documentSedinta>incheiereAmanareinitialaapronuntarii</documentSedinta><numarDocument /><dataDocument>2018-03-19T00:00:00</dataDocument></DosarSedinta><DosarSedinta><complet>C13</complet><data>2018-02-21T00:00:00</data><ora>08:30</ora><solutie>Amână cauza</solutie><solutieSumar>- termen acordat pentru traducerea anchetei sociale şi a adresei privind veniturile</solutieSumar><dataPronuntare xsi:nil="true" /><documentSedinta>incheieredesedinta</documentSedinta><numarDocument /><dataDocument>2018-02-21T00:00:00</dataDocument></DosarSedinta><DosarSedinta><complet>C13</complet><data>2018-01-23T00:00:00</data><ora>08:30</ora><solutie>Amână cauza</solutie><solutieSumar>Termen acordat pentru lipsa anchetei sociale </solutieSumar><dataPronuntare xsi:nil="true" /><documentSedinta>incheieredesedinta</documentSedinta><numarDocument /><dataDocument>2018-01-23T00:00:00</dataDocument></DosarSedinta><DosarSedinta><complet>C13</complet><data>2017-11-28T00:00:00</data><ora>08:30</ora><solutie>Amână cauza</solutie><solutieSumar>lipsă anchetă socială</solutieSumar><dataPronuntare xsi:nil="true" /><documentSedinta>incheieredesedinta</documentSedinta><numarDocument /><dataDocument>2017-11-28T00:00:00</dataDocument></DosarSedinta><DosarSedinta><complet>C13</complet><data>2017-09-25T00:00:00</data><ora>08:30</ora><solutie>Amână cauza</solutie><solutieSumar>pentru efectuarea unei comisii rogatorii</solutieSumar><dataPronuntare xsi:nil="true" /><documentSedinta>incheieredesedinta</documentSedinta><numarDocument /><dataDocument>2017-09-25T00:00:00</dataDocument></DosarSedinta><DosarSedinta><complet>C13</complet><data>2017-06-22T00:00:00</data><ora>08:30</ora><solutie>Amână cauza</solutie><solutieSumar>lipsă martor</solutieSumar><dataPronuntare xsi:nil="true" /><documentSedinta>incheieredesedinta</documentSedinta><numarDocument /><dataDocument>2017-06-22T00:00:00</dataDocument></DosarSedinta><DosarSedinta><complet>C13</complet><data>2017-06-06T00:00:00</data><ora>08:30</ora><solutie>Amână cauza</solutie><solutieSumar>pentru audierea martorei lipsă</solutieSumar><dataPronuntare xsi:nil="true" /><documentSedinta>incheieredesedinta</documentSedinta><numarDocument /><dataDocument>2017-06-06T00:00:00</dataDocument></DosarSedinta><DosarSedinta><complet>C13</complet><data>2017-05-08T00:00:00</data><ora>08:30</ora><solutie>Amână cauza</solutie><solutieSumar>pentru administrarea probelor</solutieSumar><dataPronuntare xsi:nil="true" /><documentSedinta>incheieredesedinta</documentSedinta><numarDocument /><dataDocument>2017-05-08T00:00:00</dataDocument></DosarSedinta></sedinte><caiAtac><DosarCaleAtac><dataDeclarare>2018-06-07T00:00:00</dataDeclarare><parteDeclaratoare> LUPU PETRU, </parteDeclaratoare><tipCaleAtac>Apel</tipCaleAtac></DosarCaleAtac></caiAtac><numar>4061/193/2017</numar><numarVechi /><data>2017-03-01T11:11:00</data><institutie>JudecatoriaBOTOSANI</institutie><departament>Secţia Civilă</departament><categorieCaz>Minorisifamilie</categorieCaz><stadiuProcesual>Fond</stadiuProcesual><obiect>exercitarea autorităţii părinteşti</obiect><dataModificare>2018-06-12T18:31:57.39</dataModificare><categorieCazNume>Minori şi familie</categorieCazNume><stadiuProcesualNume>Fond</stadiuProcesualNume></Dosar><Dosar><parti><DosarParte><nume>MĂRICUŢA CORINA</nume><calitateParte>Reclamant</calitateParte></DosarParte><DosarParte><nume>MIRODONE VASILE</nume><calitateParte>Pârât</calitateParte></DosarParte><DosarParte><nume>MIRODONE VASILE cu dom proc ales la av. Bîrlădeanu Marian</nume><calitateParte>Pârât</calitateParte></DosarParte></parti><sedinte><DosarSedinta><complet>C21</complet><data>2018-10-10T00:00:00</data><ora>08:30</ora><solutie>Alte soluţii</solutie><solutieSumar>Respinge cererea având ca obiect măsuri privind minorul – exercitare autoritate părintească în mod exclusiv, formulată de reclamanta Măricuţă Corina în contradictoriu pârâtul Mirodone Vasile, ca nefondată. 
Respinge cererea având ca obiect suplinire consimţământ pârât pentru călătoria minorei Mirodone Iolanda Felicia, în străinătate, inclusiv pentru emiterea şi întocmirea documentaţiei pentru paşaportul minorei, formulată de reclamanta Măricuţă Corina în contradictoriu cu pârâtul, Mirodone Vasile, ca nefondată.
Admite cererea reconvenţională, având ca obiect stabilire legături personale cu minorul, formulată de pârâtul reclamant Mirodone Vasile, în contradictoriu cu reclamanta pârâtă, Măricuţă Corina.
Obligă reclamanta pârâtă,  să permită pârâtului reclamant să aibă legături personale cu minora, Mirodone Iolanda Felicia, născută la data de 30.06.2010, în permanenţă prin contact telefonic/alt mijloc de comunicare, precum şi să îi trimită pârâtului, periodic, informaţii referitoare la copil, inclusiv fotografii recente, evaluări medicale sau şcolare, informaţii cu privire la starea de sănătate sau orice altă problemă.
Cu drept de apel în 30 de zile de la pronunţare, care se va depune la Judecătoria Botoşani.
Pronunţată în şedinţă publică, azi, 10.10.2018.
</solutieSumar><dataPronuntare>2018-10-10T00:00:00</dataPronuntare><documentSedinta>Hotarare</documentSedinta><numarDocument>4218/2018</numarDocument><dataDocument>2018-10-10T00:00:00</dataDocument></DosarSedinta><DosarSedinta><complet>C21</complet><data>2018-09-14T00:00:00</data><ora>08:30</ora><solutie>Amână cauza</solutie><solutieSumar>Amână cauza în vederea traducerii relaţiilor din străinătate. </solutieSumar><dataPronuntare>2018-09-14T00:00:00</dataPronuntare><documentSedinta>incheieredesedinta</documentSedinta><numarDocument /><dataDocument>2018-09-14T00:00:00</dataDocument></DosarSedinta><DosarSedinta><complet>C21</complet><data>2018-06-15T00:00:00</data><ora>08:30</ora><solutie>Amână cauza</solutie><solutieSumar>Amână cauza în vederea continuării cercetării judecătoreşti.</solutieSumar><dataPronuntare>2018-06-15T00:00:00</dataPronuntare><documentSedinta>incheieredesedinta</documentSedinta><numarDocument /><dataDocument>2018-06-15T00:00:00</dataDocument></DosarSedinta><DosarSedinta><complet>C21</complet><data>2018-05-21T00:00:00</data><ora>08:30</ora><solutie>Amână cauza</solutie><solutieSumar>Amână cauza în vederea continuării cercetării judecătoreşti.</solutieSumar><dataPronuntare>2018-05-21T00:00:00</dataPronuntare><documentSedinta>incheieredesedinta</documentSedinta><numarDocument /><dataDocument>2018-05-21T00:00:00</dataDocument></DosarSedinta><DosarSedinta><complet>C21</complet><data>2018-04-25T00:00:00</data><ora>08:30</ora><solutie>Amână cauza</solutie><solutieSumar>Amână cauza în vederea continuării cercetării judecătoreşti.</solutieSumar><dataPronuntare>2018-04-25T00:00:00</dataPronuntare><documentSedinta>incheieredesedinta</documentSedinta><numarDocument /><dataDocument>2018-04-25T00:00:00</dataDocument></DosarSedinta><DosarSedinta><complet>C21</complet><data>2018-03-13T00:00:00</data><ora>08:30</ora><solutie>Amână cauza</solutie><solutieSumar>Amână cauza în vederea continuării cercetării judecătoreşti.</solutieSumar><dataPronuntare>2018-03-13T00:00:00</dataPronuntare><documentSedinta>incheieredesedinta</documentSedinta><numarDocument /><dataDocument>2018-03-13T00:00:00</dataDocument></DosarSedinta><DosarSedinta><complet>C21</complet><data>2018-02-07T00:00:00</data><ora>08:30</ora><solutie>Amână cauza</solutie><solutieSumar>Amână cauza în vederea continuării cercetării propuse.  </solutieSumar><dataPronuntare>2018-02-07T00:00:00</dataPronuntare><documentSedinta>incheieredesedinta</documentSedinta><numarDocument /><dataDocument>2018-02-07T00:00:00</dataDocument></DosarSedinta><DosarSedinta><complet>C9</complet><data>2018-01-10T00:00:00</data><ora>08:30</ora><solutie>Amână cauza</solutie><solutieSumar>pentru repartizarea cauzei la completul legal învestit</solutieSumar><dataPronuntare>2018-01-10T00:00:00</dataPronuntare><documentSedinta>incheieredesedinta</documentSedinta><numarDocument /><dataDocument>2018-01-10T00:00:00</dataDocument></DosarSedinta><DosarSedinta><complet>C9</complet><data>2017-11-03T00:00:00</data><ora>08:30</ora><solutie>Amână cauza</solutie><solutieSumar>pentru administrarea probatoriului</solutieSumar><dataPronuntare>2017-11-03T00:00:00</dataPronuntare><documentSedinta>incheieredesedinta</documentSedinta><numarDocument /><dataDocument>2017-11-03T00:00:00</dataDocument></DosarSedinta><DosarSedinta><complet>C9</complet><data>2017-09-22T00:00:00</data><ora>08:30</ora><solutie>Amână cauza</solutie><solutieSumar>pentru administrarea probatoriului</solutieSumar><dataPronuntare>2017-09-22T00:00:00</dataPronuntare><documentSedinta>incheieredesedinta</documentSedinta><numarDocument /><dataDocument>2017-09-22T00:00:00</dataDocument></DosarSedinta></sedinte><caiAtac><DosarCaleAtac><dataDeclarare>2018-12-04T00:00:00</dataDeclarare><parteDeclaratoare> MĂRICUŢA CORINA, </parteDeclaratoare><tipCaleAtac>Apel</tipCaleAtac></DosarCaleAtac></caiAtac><numar>7443/193/2017</numar><numarVechi /><data>2017-04-24T11:09:00</data><institutie>JudecatoriaBOTOSANI</institutie><departament>Secţia Civilă</departament><categorieCaz>Minorisifamilie</categorieCaz><stadiuProcesual>Fond</stadiuProcesual><obiect>exercitarea autorităţii părinteşti</obiect><dataModificare>2018-12-23T21:41:19.493</dataModificare><categorieCazNume>Minori şi familie</categorieCazNume><stadiuProcesualNume>Fond</stadiuProcesualNume></Dosar><Dosar><parti><DosarParte><nume>ANGHELACHE ILIE</nume><calitateParte>Reclamant</calitateParte></DosarParte><DosarParte><nume>DASCĂLU ANCA</nume><calitateParte>Pârât</calitateParte></DosarParte></parti><sedinte><DosarSedinta><complet>C13</complet><data>2018-06-14T00:00:00</data><ora>08:30</ora><solutie>Admite in parte cererea</solutie><solutieSumar>Admite în parte acţiunea având ca obiect exercitare autoritate părintească+stabilire program vizită formulată de reclamantul-pârât ANGHELACHE ILIE în contradictoriu cu  pârâta-reclamantă DASCĂLU ANCA.
	Admite cererea reconvenţională.
	Respinge cererea reclamantului pârât de exercitare în comun a autorităţii părinteşti cu privire la minora Anghelache Daria, născută la data de 26.02.2010.
	Stabileşte un program de vizită în favoarea reclamantului pârât pentru minoră,  in urmatoarea modalitate :
-	în fiecare sâmbătă şi duminică din săptămânile impare ale lunii, de la ora 12.00 până la ora 19.00, la domiciliul reclamantului pârât.
-	două săptămâni din vacanţa de vară a fiecărui an, dacă minora va dori acest lucru.
		Majorează pensia de întreţinere stabilită în sarcina reclamantului pârât în favoarea minorei Anghelache Daria prin sentinţa civilă nr. 6572/24.06.2015 pronunţată în dosarul nr. 2913/193/2015 de la suma de 180 lei la suma de 400 lei, de la data promovării acţiunii, 04.05.2017, ?i  până la majoratul minorei. 
		Compensează cheltuielile de judecată.
		Cu apel în termen de 30 zile de la comunicare, ce se va depune la Judecătoria Botoşani,
		Pronuntata in sedinta publica azi, 14.06.2018.
</solutieSumar><dataPronuntare>2018-06-14T00:00:00</dataPronuntare><documentSedinta>Hotarare</documentSedinta><numarDocument>2768/2018</numarDocument><dataDocument>2018-06-14T00:00:00</dataDocument></DosarSedinta><DosarSedinta><complet>C13</complet><data>2018-06-11T00:00:00</data><ora>08:30</ora><solutie>Amână cauza</solutie><solutieSumar>Amână pronunţarea pentru data de 14.06.2018. 
Pronunţată în şedinţă publică, azi, 11.06.2018.</solutieSumar><dataPronuntare>2018-06-11T00:00:00</dataPronuntare><documentSedinta>incheiereAmanareinitialaapronuntarii</documentSedinta><numarDocument /><dataDocument>2018-06-11T00:00:00</dataDocument></DosarSedinta><DosarSedinta><complet>C13</complet><data>2018-04-19T00:00:00</data><ora>08:30</ora><solutie>Amână cauza</solutie><solutieSumar>Pentru a da posibilitate părţilor  să materializeze un program de legături personale redus şi verificarea de către instanţă a îndeplinirii acestei măsuri. </solutieSumar><dataPronuntare>2018-04-19T00:00:00</dataPronuntare><documentSedinta>incheieredesedinta</documentSedinta><numarDocument /><dataDocument>2018-04-19T00:00:00</dataDocument></DosarSedinta><DosarSedinta><complet>C13</complet><data>2018-03-19T00:00:00</data><ora>08:30</ora><solutie>Amână cauza</solutie><solutieSumar>termen acordat pentru audierea martorilor propuşi</solutieSumar><dataPronuntare xsi:nil="true" /><documentSedinta>incheieredesedinta</documentSedinta><numarDocument /><dataDocument>2018-03-19T00:00:00</dataDocument></DosarSedinta><DosarSedinta><complet>C13</complet><data>2018-02-13T00:00:00</data><ora>08:30</ora><solutie>Amână cauza</solutie><solutieSumar>termen acordat pentru audierea martorilor</solutieSumar><dataPronuntare xsi:nil="true" /><documentSedinta>incheieredesedinta</documentSedinta><numarDocument /><dataDocument>2018-02-13T00:00:00</dataDocument></DosarSedinta><DosarSedinta><complet>C4</complet><data>2018-01-25T00:00:00</data><ora>08:30</ora><solutie>Amână cauza</solutie><solutieSumar>În vederea redistribuirii cauzei cf Hotărârii nr. 32/21.12.2017 a Colegiului de Conducere al Judecătoriei Botoşani.</solutieSumar><dataPronuntare>2018-01-25T00:00:00</dataPronuntare><documentSedinta>incheieredesedinta</documentSedinta><numarDocument /><dataDocument>2018-01-25T00:00:00</dataDocument></DosarSedinta><DosarSedinta><complet>C4</complet><data>2017-12-15T00:00:00</data><ora>08:30</ora><solutie>Amână cauza</solutie><solutieSumar>Amână cauza în vederea administrării probei testimoniale.</solutieSumar><dataPronuntare>2017-12-15T00:00:00</dataPronuntare><documentSedinta>incheieredesedinta</documentSedinta><numarDocument /><dataDocument>2017-12-15T00:00:00</dataDocument></DosarSedinta><DosarSedinta><complet>C4</complet><data>2017-11-09T00:00:00</data><ora>08:30</ora><solutie>Amână cauza</solutie><solutieSumar>Amână cauza pentru administrarea probei testimoniale </solutieSumar><dataPronuntare xsi:nil="true" /><documentSedinta>incheieredesedinta</documentSedinta><numarDocument /><dataDocument>2017-11-09T00:00:00</dataDocument></DosarSedinta><DosarSedinta><complet>C4</complet><data>2017-10-24T00:00:00</data><ora>08:30</ora><solutie>Amână cauza</solutie><solutieSumar>Pentru administrarea probei testimoniale.</solutieSumar><dataPronuntare>2017-10-24T00:00:00</dataPronuntare><documentSedinta>incheieredesedinta</documentSedinta><numarDocument /><dataDocument>2017-10-24T00:00:00</dataDocument></DosarSedinta><DosarSedinta><complet>C4</complet><data>2017-09-12T00:00:00</data><ora>08:30</ora><solutie>Amână cauza</solutie><solutieSumar>pentru administrare probatoriului şi pentru a se emite adrese către ITM şi ONRC</solutieSumar><dataPronuntare xsi:nil="true" /><documentSedinta>incheieredesedinta</documentSedinta><numarDocument /><dataDocument>2017-09-12T00:00:00</dataDocument></DosarSedinta></sedinte><caiAtac><DosarCaleAtac><dataDeclarare>2018-12-03T00:00:00</dataDeclarare><parteDeclaratoare> ANGHELACHE ILIE, </parteDeclaratoare><tipCaleAtac>Apel</tipCaleAtac></DosarCaleAtac></caiAtac><numar>8032/193/2017</numar><numarVechi /><data>2017-05-04T12:35:00</data><institutie>JudecatoriaBOTOSANI</institutie><departament>Secţia Civilă</departament><categorieCaz>Minorisifamilie</categorieCaz><stadiuProcesual>Fond</stadiuProcesual><obiect>exercitarea autorităţii părinteşti</obiect><dataModificare>2019-01-03T18:44:55.987</dataModificare><categorieCazNume>Minori şi familie</categorieCazNume><stadiuProcesualNume>Fond</stadiuProcesualNume></Dosar><Dosar><parti><DosarParte><nume>CHIORĂSCU MONICA IULIANA</nume><calitateParte>Reclamant</calitateParte></DosarParte><DosarParte><nume>RUDIŞTEANU RADU</nume><calitateParte>Pârât</calitateParte></DosarParte></parti><sedinte><DosarSedinta><complet>C5</complet><data>2018-01-12T00:00:00</data><ora>08:30</ora><solutie>Admite cererea</solutie><solutieSumar>
Admite cererea având ca obiect schimbare măsuri privind copilul minor formulată de reclamanta Chiorăscu Monica Iuliana în contradictoriu cu pârâtul Rudişteanu Radu.
Stabileşte exercitarea în comun, de către ambele părţi a autorităţii părinteşti asupra minorei R. E.
Stabileşte un program de vizitare a minorei în favoarea reclamantei la domiciliul bunicilor materni din România, astfel :
-în timpul sărbătorilor de iarnă o săptămână  incluzând şi datele de 24 şi 25 decembrie,
-în timpul sărbătorilor de Paşti o săptămână, incluzând prima şi a doua zi de Paşti,
-în vacanţa de vară, luna iulie integral,
-6 ore, de la ora 11,00 şi până la ora 17,00, la aniversarea zilei de naştere a minorei, din data de 9 mai a fiecărui an.
Obligă pe pârât să-i permită reclamantei să ia legătura cu minora telefonic sau prin intermediul reţelelor de socializare prin punerea la dispoziţia reclamantei a unui număr de telefon al minorei sau a unei adrese de facebook sau skype.
Obligă pe pârât să-i plătească reclamantei suma de 4.650 lei cu titlu de cheltuieli de judecată.
Cu drept de apel, ce se depune la Judecătoria Botoşani, în termen de 30 de zile de la comunicare.
Pronunţată în şedinţă publică.
</solutieSumar><dataPronuntare>2018-01-12T00:00:00</dataPronuntare><documentSedinta>Hotarare</documentSedinta><numarDocument>105/2018</numarDocument><dataDocument>2018-01-12T00:00:00</dataDocument></DosarSedinta><DosarSedinta><complet>C5</complet><data>2017-11-28T00:00:00</data><ora>08:30</ora><solutie>Amână cauza</solutie><solutieSumar>Acordă termen la 12.01.2018 pentru obţinerea de relaţii privind veniturile părţilor.</solutieSumar><dataPronuntare xsi:nil="true" /><documentSedinta>incheieredesedinta</documentSedinta><numarDocument /><dataDocument>2017-11-28T00:00:00</dataDocument></DosarSedinta><DosarSedinta><complet>C5</complet><data>2017-11-02T00:00:00</data><ora>08:30</ora><solutie>Amână cauza</solutie><solutieSumar>Acordă termen la 28.11.2017 pentru administrarea probei cu interogatoriu.</solutieSumar><dataPronuntare xsi:nil="true" /><documentSedinta>incheieredesedinta</documentSedinta><numarDocument /><dataDocument>2017-11-02T00:00:00</dataDocument></DosarSedinta><DosarSedinta><complet>C5</complet><data>2017-09-29T00:00:00</data><ora>08:30</ora><solutie>Amână cauza</solutie><solutieSumar>Amână judecarea cauzei şi acordă termen la 02.11.2017 pentru administrarea probatoriului. </solutieSumar><dataPronuntare xsi:nil="true" /><documentSedinta>incheieredesedinta</documentSedinta><numarDocument /><dataDocument>2017-09-29T00:00:00</dataDocument></DosarSedinta></sedinte><caiAtac><DosarCaleAtac><dataDeclarare>2018-02-08T00:00:00</dataDeclarare><parteDeclaratoare> RUDIŞTEANU RADU, </parteDeclaratoare><tipCaleAtac>Apel</tipCaleAtac></DosarCaleAtac></caiAtac><numar>11365/193/2017</numar><numarVechi /><data>2017-06-20T13:25:00</data><institutie>JudecatoriaBOTOSANI</institutie><departament>Secţia Civilă</departament><categorieCaz>Minorisifamilie</categorieCaz><stadiuProcesual>Fond</stadiuProcesual><obiect>exercitarea autorităţii părinteşti</obiect><dataModificare>2018-05-02T18:51:09.25</dataModificare><categorieCazNume>Minori şi familie</categorieCazNume><stadiuProcesualNume>Fond</stadiuProcesualNume></Dosar><Dosar><parti><DosarParte><nume>IŢCU MIHAELA - MARICELA</nume><calitateParte>Reclamant</calitateParte></DosarParte><DosarParte><nume>KARAKAŞ ALI</nume><calitateParte>Pârât</calitateParte></DosarParte><DosarParte><nume>KARAKAŞ ALI,  PRIN CURATOR  AV. BOSÂNCEANU ABABEI CONSTANTIN</nume><calitateParte>Pârât</calitateParte></DosarParte></parti><sedinte><DosarSedinta><complet>C15</complet><data>2019-03-06T00:00:00</data><ora>08:30</ora><solutie>Alte soluţii</solutie><solutieSumar>Respinge actiunea ca nefiind de competenta instantei romane..
Cu  drept de recurs in termen de 30 de zile de la comunicare, ce se depune la Judecatoria Botosani
Pronunţată prin punerea soluţiei la dispoziţia părţilor de către grefa instanţei
</solutieSumar><dataPronuntare>2019-03-06T00:00:00</dataPronuntare><documentSedinta>Hotarare</documentSedinta><numarDocument>728/2019</numarDocument><dataDocument>2019-03-06T00:00:00</dataDocument></DosarSedinta><DosarSedinta><complet>C13</complet><data>2019-01-31T00:00:00</data><ora>08:30</ora><solutie>Amână cauza</solutie><solutieSumar>Având în vedere dispoziţiile art.4 din Hotărârea nr. 37/21.12.2018 a Colegiului de conducere al Judecătoriei Botoşani ( prin care s-a dispus redistribuirea ciclică a dosarelor aflate pe rolul completului C 13/CN13/CR13/CU13 – judecător Ichim Oana Maria, completelor de judecată din cadrul Secţiei Civile, în ordine cronologică), văzând şi procesul – verbal din data de 22.01.2019 în conformitate cu care redistribuirea se va face începând cu completul C 16, complet care urmează după redistribuirea efectuată prin procesul verbal (1) din data de 03.01.2019 (dosar nr.14791/193/2018) instanţa apreciază că este justificată acordarea unui termen în vederea continuării judecării cauzei de către completul învestit în urma redistribuirii, respectiv C 15

</solutieSumar><dataPronuntare>2019-01-31T00:00:00</dataPronuntare><documentSedinta>incheieredesedinta</documentSedinta><numarDocument /><dataDocument>2019-01-31T00:00:00</dataDocument></DosarSedinta><DosarSedinta><complet>C13</complet><data>2018-11-28T00:00:00</data><ora>08:30</ora><solutie>Amână cauza</solutie><solutieSumar>- termen pentru a se reveni cu ancheta socială în Anglia</solutieSumar><dataPronuntare xsi:nil="true" /><documentSedinta>incheieredesedinta</documentSedinta><numarDocument /><dataDocument>2018-11-28T00:00:00</dataDocument></DosarSedinta><DosarSedinta><complet>C13</complet><data>2018-10-25T00:00:00</data><ora>08:30</ora><solutie>Amână cauza</solutie><solutieSumar>- termen acordat pentru lipsa anchetei sociale din Anglia</solutieSumar><dataPronuntare xsi:nil="true" /><documentSedinta>incheieredesedinta</documentSedinta><numarDocument /><dataDocument>2018-10-25T00:00:00</dataDocument></DosarSedinta><DosarSedinta><complet>C13</complet><data>2018-09-13T00:00:00</data><ora>08:30</ora><solutie>Amână cauza</solutie><solutieSumar>- lipsă anchetă socială din Anglia</solutieSumar><dataPronuntare xsi:nil="true" /><documentSedinta>incheieredesedinta</documentSedinta><numarDocument /><dataDocument>2018-09-13T00:00:00</dataDocument></DosarSedinta><DosarSedinta><complet>C13</complet><data>2018-06-11T00:00:00</data><ora>08:30</ora><solutie>Amână cauza</solutie><solutieSumar>Pentru lipsa  anchetei sociale şi   a martorilor.</solutieSumar><dataPronuntare>2018-06-11T00:00:00</dataPronuntare><documentSedinta>incheieredesedinta</documentSedinta><numarDocument /><dataDocument>2018-06-11T00:00:00</dataDocument></DosarSedinta><DosarSedinta><complet>C13</complet><data>2018-05-07T00:00:00</data><ora>08:30</ora><solutie>Amână cauza</solutie><solutieSumar>-	termen acordat pentru administrarea probelor propuse şi încuviinţate </solutieSumar><dataPronuntare xsi:nil="true" /><documentSedinta>incheieredesedinta</documentSedinta><numarDocument /><dataDocument>2018-05-07T00:00:00</dataDocument></DosarSedinta><DosarSedinta><complet>C13</complet><data>2018-04-19T00:00:00</data><ora>08:30</ora><solutie>Amână cauza</solutie><solutieSumar>Pentru a se da posibilitate reclamantei să facăp dovada achitării  onorariului curatorului desemnat pentru pârât. </solutieSumar><dataPronuntare>2018-04-19T00:00:00</dataPronuntare><documentSedinta>incheieredesedinta</documentSedinta><numarDocument /><dataDocument>2018-04-19T00:00:00</dataDocument></DosarSedinta><DosarSedinta><complet>C13</complet><data>2018-03-09T00:00:00</data><ora>08:30</ora><solutie>Amână cauza</solutie><solutieSumar>termen acordat pentru redactarea cererii de ordonanţă presedintială</solutieSumar><dataPronuntare xsi:nil="true" /><documentSedinta>incheieredesedinta</documentSedinta><numarDocument /><dataDocument>2018-03-09T00:00:00</dataDocument></DosarSedinta><DosarSedinta><complet>C4</complet><data>2017-11-09T00:00:00</data><ora>08:30</ora><solutie>411 NCPC/242 CPC</solutie><solutieSumar>În baza art. 411 alin.1 pct. 2 C.proc.civ., dispune suspendarea judecăţii cauzei.
Cu drept de recurs pe toată durata suspendării cursului procesului, cererea de recurs urmând a se depune la Judecătoria Botoşani.
Pronunţată în şedinţă publică azi, 09.11.2017.
</solutieSumar><dataPronuntare>2017-11-09T00:00:00</dataPronuntare><documentSedinta>incheiereSuspendare</documentSedinta><numarDocument /><dataDocument>2017-11-09T00:00:00</dataDocument></DosarSedinta><DosarSedinta><complet>C4</complet><data>2017-10-06T00:00:00</data><ora>08:30</ora><solutie>Amână cauza</solutie><solutieSumar>Amână cauza la data de 09.11.2017 pentru administrare de probe.</solutieSumar><dataPronuntare>2017-10-06T00:00:00</dataPronuntare><documentSedinta>incheieredesedinta</documentSedinta><numarDocument /><dataDocument>2017-10-06T00:00:00</dataDocument></DosarSedinta></sedinte><numar>13077/193/2017</numar><numarVechi /><data>2017-07-11T14:05:00</data><institutie>JudecatoriaBOTOSANI</institutie><departament>Secţia Civilă</departament><categorieCaz>Minorisifamilie</categorieCaz><stadiuProcesual>Fond</stadiuProcesual><obiect>exercitarea autorităţii părinteşti</obiect><dataModificare>2019-03-15T16:27:02.143</dataModificare><categorieCazNume>Minori şi familie</categorieCazNume><stadiuProcesualNume>Fond</stadiuProcesualNume></Dosar><Dosar><parti><DosarParte><nume>ROBOTĂ MARINELA</nume><calitateParte>Reclamant</calitateParte></DosarParte><DosarParte><nume>BURCEAG AUREL</nume><calitateParte>Pârât</calitateParte></DosarParte></parti><sedinte><DosarSedinta><complet>C7</complet><data>2018-02-12T00:00:00</data><ora>08:30</ora><solutie>Admite in parte cererea</solutie><solutieSumar>Admite în parte cererea având ca obiect modificare măsuri privind copilul minor formulată de reclamanta Robotă Marinela în contradictoriu cu pârâtul Burceag Aurel.
În baza art.436 al.2 C.p.c. constată că pârâtul a recunoscut pretenţia reclamantei de exercitare în comuna a autorităţii părinteşti cu privire la minorul Burceag Sebastian Aurel ns. La data de 25.03.2003.
În baza art.437 al.1 C.p.c. dispoziţia anterioară de consfinţire a recunoaşterii pârâtului poate fi atacată numai cu recurs, ce se depune la Judecătoria Botoşani în termen de 30 de zile de la comunicare.
Admite în parte cererea de stabilire program vizitare minor formulată de reclamantă în contradictoriu cu pârâtul, după următorul program :
-în perioada 01-31 august a fiecărui an la domiciliul bunicii materne din judeţul Botoşani.
Cu drept de apel, ce se depune la Judecătoria Botoşani, în termen de 30 de zile de la comunicare.
Pronunţată în şedinţă publică.

</solutieSumar><dataPronuntare>2018-02-12T00:00:00</dataPronuntare><documentSedinta>Hotarare</documentSedinta><numarDocument>597/2018</numarDocument><dataDocument>2018-02-12T00:00:00</dataDocument></DosarSedinta><DosarSedinta><complet>C7</complet><data>2018-02-02T00:00:00</data><ora>08:30</ora><solutie>Amână pronunţarea</solutie><solutieSumar>Amana pronunţarea la data de 12.02.2018.
Pronunţată în şedinţa publică din 02.02.2018.</solutieSumar><dataPronuntare>2018-02-02T00:00:00</dataPronuntare><documentSedinta>incheiereAmanareinitialaapronuntarii</documentSedinta><numarDocument /><dataDocument>2018-02-02T00:00:00</dataDocument></DosarSedinta><DosarSedinta><complet>C6</complet><data>2018-01-15T00:00:00</data><ora>08:30</ora><solutie>Amână cauza</solutie><solutieSumar>Având în vedere Hotărârea nr. 32 din 21.12.2017 a Colegiului de Conducere al Judecătoriei Botoşani, prin care s-a aprobat redistribuirea ciclică a dosarelor aflate pe rolul completului C6/CN6/CR6/CU6, ca urmare a desfiinţării, prezenta cauză va fi redistribuită la complet C.7 - BA, cu termen de judecată la 2.02.2018. 
</solutieSumar><dataPronuntare xsi:nil="true" /><documentSedinta>incheieredesedinta</documentSedinta><numarDocument /><dataDocument>2018-01-15T00:00:00</dataDocument></DosarSedinta><DosarSedinta><complet>C6</complet><data>2017-12-13T00:00:00</data><ora>08:30</ora><solutie>Amână cauza</solutie><solutieSumar>Încuviinţează cererea apărătorului reclamantei, de acordare termen pentru prezenţa martorului propus.</solutieSumar><dataPronuntare xsi:nil="true" /><documentSedinta>incheieredesedinta</documentSedinta><numarDocument /><dataDocument>2017-12-13T00:00:00</dataDocument></DosarSedinta><DosarSedinta><complet>C6</complet><data>2017-11-08T00:00:00</data><ora>08:30</ora><solutie>Amână cauza</solutie><solutieSumar>Acordă termen pentru administrarea probelor propuse de părţi.</solutieSumar><dataPronuntare xsi:nil="true" /><documentSedinta>incheieredesedinta</documentSedinta><numarDocument /><dataDocument>2017-11-08T00:00:00</dataDocument></DosarSedinta></sedinte><caiAtac><DosarCaleAtac><dataDeclarare>2018-04-02T00:00:00</dataDeclarare><parteDeclaratoare> ROBOTĂ MARINELA, </parteDeclaratoare><tipCaleAtac>Apel</tipCaleAtac></DosarCaleAtac><DosarCaleAtac><dataDeclarare>2018-03-30T00:00:00</dataDeclarare><parteDeclaratoare> ROBOTĂ MARINELA, </parteDeclaratoare><tipCaleAtac>Apel</tipCaleAtac></DosarCaleAtac><DosarCaleAtac><dataDeclarare>2018-03-29T00:00:00</dataDeclarare><parteDeclaratoare> BURCEAG AUREL, </parteDeclaratoare><tipCaleAtac>Apel</tipCaleAtac></DosarCaleAtac></caiAtac><numar>14603/193/2017</numar><numarVechi /><data>2017-08-03T11:40:00</data><institutie>JudecatoriaBOTOSANI</institutie><departament>Secţia Civilă</departament><categorieCaz>Minorisifamilie</categorieCaz><stadiuProcesual>Fond</stadiuProcesual><obiect>exercitarea autorităţii părinteşti</obiect><dataModificare>2018-04-12T18:57:15.31</dataModificare><categorieCazNume>Minori şi familie</categorieCazNume><stadiuProcesualNume>Fond</stadiuProcesualNume></Dosar><Dosar><parti><DosarParte><nume>CUDALBA VIRGINIA la fam. Ciugolea Maria</nume><calitateParte>Reclamant</calitateParte></DosarParte><DosarParte><nume>CUDALBĂ GICĂ</nume><calitateParte>Pârât</calitateParte></DosarParte></parti><sedinte><DosarSedinta><complet>C14</complet><data>2018-10-25T00:00:00</data><ora>10:00</ora><solutie>Constată perimată cererea</solutie><solutieSumar>Admite excepţia perimării cererii de chemare în judecată, invocată din oficiu.
Constată perimată cererea de chemare în judecată.
Cu drept de a formula recurs în 5 zile de la pronunţare.
Cererea de recurs se va depune la Judecătoria Botoşani.
Pronunţată în şedinţă publică, azi, 25.10.2018.
</solutieSumar><dataPronuntare>2018-10-25T00:00:00</dataPronuntare><documentSedinta>Hotarare</documentSedinta><numarDocument>4508/2018</numarDocument><dataDocument>2018-10-25T00:00:00</dataDocument></DosarSedinta><DosarSedinta><complet>C14</complet><data>2018-02-22T00:00:00</data><ora>10:00</ora><solutie>411 NCPC/242 CPC</solutie><solutieSumar>În temeiul dispoziţiilor art. 411 alin (1) pct. 2 Cod procedură civilă, suspendă judecarea acţiunii formulate de reclamanta Cudalbă Virginia în contradictoriu cu pârâtul Cudalbă Gică.
Cu drept de recurs pe toată perioada suspendării, ce se va depune la Judecătoria Botoşani.
Pronunţată în şedinţă publică, azi, 22.02.2018.
</solutieSumar><dataPronuntare>2018-02-22T00:00:00</dataPronuntare><documentSedinta>incheiereSuspendare</documentSedinta><numarDocument /><dataDocument>2018-02-22T00:00:00</dataDocument></DosarSedinta><DosarSedinta><complet>C4</complet><data>2018-02-01T00:00:00</data><ora>10:00</ora><solutie>Amână cauza</solutie><solutieSumar>În vederea redistribuirii cauzei cf Hotărârii nr. 32/21.12.2017 a Colegiului de Conducere al Judecătoriei Botoşani.</solutieSumar><dataPronuntare>2018-02-01T00:00:00</dataPronuntare><documentSedinta>incheieredesedinta</documentSedinta><numarDocument /><dataDocument>2018-02-01T00:00:00</dataDocument></DosarSedinta><DosarSedinta><complet>C4</complet><data>2017-12-05T00:00:00</data><ora>08:30</ora><solutie>Amână cauza</solutie><solutieSumar>Amână cauza pentru a se depune dovada mandatului special de avocat </solutieSumar><dataPronuntare xsi:nil="true" /><documentSedinta>incheieredesedinta</documentSedinta><numarDocument /><dataDocument>2017-12-05T00:00:00</dataDocument></DosarSedinta></sedinte><numar>15580/193/2017</numar><numarVechi /><data>2017-08-24T12:46:00</data><institutie>JudecatoriaBOTOSANI</institutie><departament>Secţia Civilă</departament><categorieCaz>Minorisifamilie</categorieCaz><stadiuProcesual>Fond</stadiuProcesual><obiect>exercitarea autorităţii părinteşti SUPLINIRE CONSIMŢĂMÂNT</obiect><dataModificare>2018-11-24T11:19:17.61</dataModificare><categorieCazNume>Minori şi familie</categorieCazNume><stadiuProcesualNume>Fond</stadiuProcesualNume></Dosar><Dosar><parti><DosarParte><nume>IORGA MARIANA - GIORGIANA</nume><calitateParte>Reclamant</calitateParte></DosarParte><DosarParte><nume>MAYOR PICON FELIPE LA FAM MAYOR PICON</nume><calitateParte>Pârât</calitateParte></DosarParte></parti><sedinte><DosarSedinta><complet>C21</complet><data>2018-10-18T00:00:00</data><ora>08:30</ora><solutie>Constată perimată cererea</solutie><solutieSumar>	Constată perimată acţiunea având ca obiect exercitare autoritate părinteasca.
	Cu drept de recurs în termen de 5 zile de la pronunţare, care se depune la Judecătoria Botoşani.
	Pronunţată în şedinţă publică, azi, 18.10.2018.
</solutieSumar><dataPronuntare>2018-10-18T00:00:00</dataPronuntare><documentSedinta>Hotarare</documentSedinta><numarDocument>4379/2018</numarDocument><dataDocument>2018-10-18T00:00:00</dataDocument></DosarSedinta><DosarSedinta><complet>C21</complet><data>2017-12-14T00:00:00</data><ora>08:30</ora><solutie>Amână cauza</solutie><solutieSumar>Termenul a fost preschimbat la data de 20.11.2017.</solutieSumar><dataPronuntare>2017-12-14T00:00:00</dataPronuntare><documentSedinta>incheieredesedinta</documentSedinta><numarDocument /><dataDocument>2017-12-14T00:00:00</dataDocument></DosarSedinta><DosarSedinta><complet>C21</complet><data>2017-11-20T00:00:00</data><ora>13:00</ora><solutie>Alte cauze</solutie><solutieSumar>Suspendă cauza, având ca obiect măsuri privind minorul, formulată de reclamanta Iorga Mariana-Giorgiana în contradictotiu cu pârâtul Felipe Mayor Picon, în temeiul art. 16 din Convenţia de la Haga din 25 octombrie 1980 privind aspectele civile ale răpirii internaţionale de copii, până la soluţionarea definitivă a dosarului nr. 40683/3/2017 aflat pe rolul Tribunalului Bucureşti,  având ca obiect răpire internaţională de copii.
             Cu drept de recurs pe toată perioada suspendării, care se va depune la Judecătoria Botoşani.
	 Pronunţată în şedinţă publică, azi, 20.11.2017.

 
</solutieSumar><dataPronuntare>2017-11-20T00:00:00</dataPronuntare><documentSedinta>incheiereSuspendare</documentSedinta><numarDocument /><dataDocument>2017-11-20T00:00:00</dataDocument></DosarSedinta><DosarSedinta><complet>C21</complet><data>2017-11-17T00:00:00</data><ora>08:30</ora><solutie>Amână cauza</solutie><solutieSumar>Admite cererea de preschimbare termen, invocată din oficiu.
Preschimbă termenul de judecată stabilit pentru data de 14.12.2017, în vederea soluţionării cererii având ca obiect măsuri privind minorul, în dosarul nr. 15686/193/2017, pentru termenul de judecată din data de 20.11.2017, ora 13.00.
Citarea părţilor pentru noul termen de judecată din data de 20.11.2017.
Dată în camera de consiliu şi pronunţată în şedinţă publică, azi, 17.11.2017.</solutieSumar><dataPronuntare>2017-11-17T00:00:00</dataPronuntare><documentSedinta>incheieredesedinta</documentSedinta><numarDocument /><dataDocument>2017-11-17T00:00:00</dataDocument></DosarSedinta><DosarSedinta><complet>C21</complet><data>2017-11-16T00:00:00</data><ora>08:30</ora><solutie>Amână cauza</solutie><solutieSumar>Amână cauza în vederea continuării cercetării judecătoreşti</solutieSumar><dataPronuntare>2017-11-16T00:00:00</dataPronuntare><documentSedinta>incheieredesedinta</documentSedinta><numarDocument /><dataDocument>2017-11-16T00:00:00</dataDocument></DosarSedinta></sedinte><numar>15686/193/2017</numar><numarVechi /><data>2017-08-29T11:22:00</data><institutie>JudecatoriaBOTOSANI</institutie><departament>Secţia Civilă</departament><categorieCaz>Minorisifamilie</categorieCaz><stadiuProcesual>Fond</stadiuProcesual><obiect>exercitarea autorităţii părinteşti</obiect><dataModificare>2018-12-23T21:41:47.07</dataModificare><categorieCazNume>Minori şi familie</categorieCazNume><stadiuProcesualNume>Fond</stadiuProcesualNume></Dosar><Dosar><parti><DosarParte><nume>SANDULEAC ANA</nume><calitateParte>Reclamant</calitateParte></DosarParte><DosarParte><nume>GRECU BOGDAN GABRIEL</nume><calitateParte>Pârât</calitateParte></DosarParte></parti><sedinte><DosarSedinta><complet>C13</complet><data>2018-03-19T00:00:00</data><ora>08:30</ora><solutie>Admite cererea</solutie><solutieSumar>Admite acţiunea având ca obiect exercitarea autorităţii părinteşti , stabilire domiciliu minor şi stabilire pensie de întreţinere  formulată de reclamanta SĂNDULEAC ANA în contradictoriu cu pârâtul GRECU BOGDAN GABRIEL.
Stabileşte ca autoritatea părintească privind minora Grecu Raluca Gabriela , născută la data de 08.11.2015  să fie exercitată în comun , de ambii părinţi.
Stabileşte domiciliul minorei la reclamantă.
Obligă pârâtul să plătească reclamantei pentru minora Grecu Raluca Gabriela , născută la data de 08.11.2015 o  pensie de întreţinere în cuantum de 268 lei lunar, începând cu data introducerii acţiunii - 06.09.2017 si  până la majoratul minorei.
Respinge cererea reconvenţională formulată de pârâtul-reclamant Grecu Bogdan Gabriel în contradictoriu cu reclamanta-pârâtă Sănduleac Ana , ca nefondată.
Obligă pârâtul la plata sumei de 1020 lei , cu titlu de cheltuieli de judecată, reprezentând taxă timbru acţiune şi onorariu avocat.
Cu apel, în termen de 30 zile de la comunicare, ce se va depune la Judecatoria Botoşani.
Pronunţată în şedinţa publică din data de 19.03.2018.
</solutieSumar><dataPronuntare>2018-03-19T00:00:00</dataPronuntare><documentSedinta>Hotarare</documentSedinta><numarDocument>1246/2018</numarDocument><dataDocument>2018-03-19T00:00:00</dataDocument></DosarSedinta><DosarSedinta><complet>C13</complet><data>2018-02-13T00:00:00</data><ora>08:30</ora><solutie>Amână cauza</solutie><solutieSumar>termen acordat pentru a se reveni la relaţii şi pentru audierea martorilor</solutieSumar><dataPronuntare xsi:nil="true" /><documentSedinta>incheieredesedinta</documentSedinta><numarDocument /><dataDocument>2018-02-13T00:00:00</dataDocument></DosarSedinta><DosarSedinta><complet>C13</complet><data>2018-01-11T00:00:00</data><ora>08:30</ora><solutie>Amână cauza</solutie><solutieSumar>termen acordat pentru administrarea probelor propuse şi încuviinţate </solutieSumar><dataPronuntare xsi:nil="true" /><documentSedinta>incheieredesedinta</documentSedinta><numarDocument /><dataDocument>2018-01-11T00:00:00</dataDocument></DosarSedinta><DosarSedinta><complet>C13</complet><data>2017-11-07T00:00:00</data><ora>08:30</ora><solutie>Amână cauza</solutie><solutieSumar>pentru timbrarea cererii reconvenţionale</solutieSumar><dataPronuntare xsi:nil="true" /><documentSedinta>incheieredesedinta</documentSedinta><numarDocument /><dataDocument>2017-11-07T00:00:00</dataDocument></DosarSedinta></sedinte><caiAtac><DosarCaleAtac><dataDeclarare>2018-05-15T00:00:00</dataDeclarare><parteDeclaratoare> GRECU BOGDAN GABRIEL, </parteDeclaratoare><tipCaleAtac>Apel</tipCaleAtac></DosarCaleAtac></caiAtac><numar>16150/193/2017</numar><numarVechi /><data>2017-09-06T10:56:00</data><institutie>JudecatoriaBOTOSANI</institutie><departament>Secţia Civilă</departament><categorieCaz>Minorisifamilie</categorieCaz><stadiuProcesual>Fond</stadiuProcesual><obiect>exercitarea autorităţii părinteşti</obiect><dataModificare>2018-06-08T18:13:52.4</dataModificare><categorieCazNume>Minori şi familie</categorieCazNume><stadiuProcesualNume>Fond</stadiuProcesualNume></Dosar><Dosar><parti><DosarParte><nume>CRUCIANU FLORINA-ALINA</nume><calitateParte>Reclamant</calitateParte></DosarParte><DosarParte><nume>ICHIM VASILE</nume><calitateParte>Pârât</calitateParte></DosarParte></parti><sedinte><DosarSedinta><complet>C21</complet><data>2018-09-24T00:00:00</data><ora>08:30</ora><solutie>Admite in parte cererea</solutie><solutieSumar>Admite în parte, acţiunea având ca obiect măsuri privind minorul, formulată de reclamanta Crucianu Florina Alina în contradictoriu cu pârâtul Ichim Vasile. 
Admite în parte cererea reconvenţională, formulată de pârâtul reclamant Ichim Vasile în contradictoriu cu reclamanta pârâtă, Crucianu Florina Alina.
Dispune ca autoritatea părintească asupra minorului Ichim Remus născut la data de ..., să fie exercitată exclusiv de către mama reclamantă.
Stabileşte locuinţa minorului Ichim Remus născut la data de ...la locuinţa mamei.
Obligă pârâtul să plătească reclamantei, pentru minorul Ichim Remus născut la data de ..., cu titlu de pensie de întreţinere suma de 150 euro lunar de la data introducerii acţiunii, respectiv de la data de 14.09.2017 şi până la majoratul minorului.
Respinge restul pretenţiilor reclamantei ca nefondate.
Obligă reclamanta-pârâtă să permită pârâtului-reclamant să aibă legături personale cu minorul, atât cât permite starea de sănătate a acestuia, sub forma vizitelor dar şi a petrecerii împreună cu aceasta în alte locaţii,  diferite decât  locuinţa mamei, respectiv la domiciliul tatălui sau locaţii de petrecere a timpului liber adecvat pentru vârsta şi nevoile minorului, cu posibilitatea pentru mama pârâtă-reclamantă de a se interesa de starea de sănătate a minorului astfel:
•	în prima şi a treia săptămână din lună de la orele 1900 la orele 1500;
•	a doua zi de paşti şi de Crăciun de la orele 1000 la orele 1800;
•	în perioada 01.07 – 31.08 a fiecărui an;
•	participarea la zilele de naştere şi onomastice ale minorului
•	în restul timpului, prin contact telefonic şi prin informarea de îndată a tatălui despre starea de sănătate a minorului şi a oricărei probleme intervenite în statutul său social şi juridic;
Respinge restul pretenţiilor pârâtului-reclamant ca nefondate.
Compensează cheltuielile de judecată.
Cu drept de apel în 30 de zile de la comunicare, care se va depune la Judecătoria Botoşani.
Pronunţată în şedinţă publică, azi, 24.09.2018.
</solutieSumar><dataPronuntare>2018-09-24T00:00:00</dataPronuntare><documentSedinta>Hotarare</documentSedinta><numarDocument>3863/2018</numarDocument><dataDocument>2018-09-24T00:00:00</dataDocument></DosarSedinta><DosarSedinta><complet>C21</complet><data>2018-06-25T00:00:00</data><ora>08:30</ora><solutie>Amână cauza</solutie><solutieSumar>Amână cauza în vederea revenirii cu Adresă către autoritatea din Italia. </solutieSumar><dataPronuntare>2018-06-25T00:00:00</dataPronuntare><documentSedinta>incheieredesedinta</documentSedinta><numarDocument /><dataDocument>2018-06-25T00:00:00</dataDocument></DosarSedinta><DosarSedinta><complet>C21</complet><data>2018-05-30T00:00:00</data><ora>08:30</ora><solutie>Amână cauza</solutie><solutieSumar>Amână cauza în vederea revenirii cu Adresă către organele abilitate.</solutieSumar><dataPronuntare>2018-05-30T00:00:00</dataPronuntare><documentSedinta>incheieredesedinta</documentSedinta><numarDocument /><dataDocument>2018-05-30T00:00:00</dataDocument></DosarSedinta><DosarSedinta><complet>C21</complet><data>2018-05-03T00:00:00</data><ora>08:30</ora><solutie>Amână cauza</solutie><solutieSumar>Amână cauza în vederea continuării cercetării judecătoreşti.</solutieSumar><dataPronuntare>2018-05-03T00:00:00</dataPronuntare><documentSedinta>incheieredesedinta</documentSedinta><numarDocument /><dataDocument>2018-05-03T00:00:00</dataDocument></DosarSedinta><DosarSedinta><complet>C21</complet><data>2018-03-21T00:00:00</data><ora>08:30</ora><solutie>Amână cauza</solutie><solutieSumar>Amână cauza în vederea depunerii la dosar a relaţiilor din străinătate.</solutieSumar><dataPronuntare>2018-03-21T00:00:00</dataPronuntare><documentSedinta>incheieredesedinta</documentSedinta><numarDocument /><dataDocument>2018-03-21T00:00:00</dataDocument></DosarSedinta><DosarSedinta><complet>C21</complet><data>2018-02-15T00:00:00</data><ora>08:30</ora><solutie>Amână cauza</solutie><solutieSumar>Amână cauza în vederea continuării cercetării judecătoreşti.</solutieSumar><dataPronuntare>2018-02-15T00:00:00</dataPronuntare><documentSedinta>incheieredesedinta</documentSedinta><numarDocument /><dataDocument>2018-02-15T00:00:00</dataDocument></DosarSedinta><DosarSedinta><complet>C21</complet><data>2018-01-23T00:00:00</data><ora>08:30</ora><solutie>Amână cauza</solutie><solutieSumar>Amână cauza în vederea continuării cercetării judecătoreşti.</solutieSumar><dataPronuntare>2018-01-23T00:00:00</dataPronuntare><documentSedinta>incheieredesedinta</documentSedinta><numarDocument /><dataDocument>2018-01-23T00:00:00</dataDocument></DosarSedinta><DosarSedinta><complet>C21</complet><data>2017-12-06T00:00:00</data><ora>08:30</ora><solutie>Amână cauza</solutie><solutieSumar>Amână cauza în vederea continuării cercetării judecătoreşti.</solutieSumar><dataPronuntare>2017-12-06T00:00:00</dataPronuntare><documentSedinta>incheieredesedinta</documentSedinta><numarDocument /><dataDocument>2017-12-06T00:00:00</dataDocument></DosarSedinta></sedinte><caiAtac><DosarCaleAtac><dataDeclarare>2018-11-06T00:00:00</dataDeclarare><parteDeclaratoare> CRUCIANU FLORINA-ALINA, </parteDeclaratoare><tipCaleAtac>Apel</tipCaleAtac></DosarCaleAtac></caiAtac><numar>16515/193/2017</numar><numarVechi /><data>2017-09-14T09:55:00</data><institutie>JudecatoriaBOTOSANI</institutie><departament>Secţia Civilă</departament><categorieCaz>Minorisifamilie</categorieCaz><stadiuProcesual>Fond</stadiuProcesual><obiect>exercitarea autorităţii părinteşti</obiect><dataModificare>2018-12-24T00:31:40.407</dataModificare><categorieCazNume>Minori şi familie</categorieCazNume><stadiuProcesualNume>Fond</stadiuProcesualNume></Dosar><Dosar><parti><DosarParte><nume>MOLDOVANU AURICA</nume><calitateParte>Reclamant</calitateParte></DosarParte><DosarParte><nume>DUMITRAŞ MARIA</nume><calitateParte>Pârât</calitateParte></DosarParte></parti><sedinte><DosarSedinta><complet>C17</complet><data>2019-09-10T00:00:00</data><ora>09:00</ora><solutie>Respinge cererea</solutie><solutieSumar>Respinge cererile ca neîntemeiate.
Respinge cererea de plată a cheltuielilor de judecată formulată de pârâtă.
Cu drept de apel în termen de 30 zile de la comunicare, care se depune la Judecătoria Botoşani.
Pronunţată prin punerea soluţiei la dispoziţia părţilor prin mijlocirea grefei instanţei în data de 10.09.2019.

</solutieSumar><dataPronuntare>2019-09-10T00:00:00</dataPronuntare><documentSedinta>Hotarare</documentSedinta><numarDocument>3420/2019</numarDocument><dataDocument>2019-09-10T00:00:00</dataDocument></DosarSedinta><DosarSedinta><complet>C17</complet><data>2019-09-03T00:00:00</data><ora>08:30</ora><solutie>Amână pronunţarea</solutie><solutieSumar>Amână pronunţarea pentru data de 10.09.2019. Pronunţată în şedinţă publică azi, 03.09.2019.</solutieSumar><dataPronuntare>2019-09-03T00:00:00</dataPronuntare><documentSedinta>incheiereAmanareinitialaapronuntarii</documentSedinta><numarDocument /><dataDocument>2019-09-03T00:00:00</dataDocument></DosarSedinta><DosarSedinta><complet>C17</complet><data>2019-06-24T00:00:00</data><ora>08:30</ora><solutie>Amână cauza</solutie><solutieSumar>În vederea continuării cercetării judecătoreşti, se va acorda un nou termen de judecată. </solutieSumar><dataPronuntare>2019-06-24T00:00:00</dataPronuntare><documentSedinta>incheieredesedinta</documentSedinta><numarDocument /><dataDocument>2019-06-24T00:00:00</dataDocument></DosarSedinta><DosarSedinta><complet>C17</complet><data>2019-03-15T00:00:00</data><ora>08:30</ora><solutie>Amână cauza</solutie><solutieSumar>În vederea administrării probei cu comisie rogatorie în Italia, pentru a se obţine informaţii cu privire la alocaţia încasată de pârâtă pentru copil, va acorda un nou termen de judecată.</solutieSumar><dataPronuntare>2019-03-15T00:00:00</dataPronuntare><documentSedinta>incheieredesedinta</documentSedinta><numarDocument /><dataDocument>2019-03-15T00:00:00</dataDocument></DosarSedinta><DosarSedinta><complet>C17</complet><data>2019-02-01T00:00:00</data><ora>08:30</ora><solutie>Amână cauza</solutie><solutieSumar>În vederea administrării probatoriului,  se va acorda un nou termen de judecată. </solutieSumar><dataPronuntare>2019-02-01T00:00:00</dataPronuntare><documentSedinta>incheieredesedinta</documentSedinta><numarDocument /><dataDocument>2019-02-01T00:00:00</dataDocument></DosarSedinta><DosarSedinta><complet>C13</complet><data>2019-01-11T00:00:00</data><ora>08:30</ora><solutie>Amână cauza</solutie><solutieSumar>Având în vedere dispoziţiile art. 4 din Hotărârea nr. 37/21.12.2018 a Colegiului de conducere al Judecătoriei Botoşani (prin care s-a dispus redistribuirea ciclică a dosarelor aflate pe rolul completului C 13, completelor de judecată din cadrul Secţiei Civile, în ordine cronologică), văzând şi Procesul – verbal din data de 08.01.2019 în conformitate cu care redistribuirea se va face începând cu completul C 16, instanţa apreciază că este justificată acordarea unui termen în vederea continuării judecării cauzei de către completul învestit în urma redistribuirii, respectiv C17 - BI, cu termen la data de 01.02.2019. </solutieSumar><dataPronuntare>2019-01-11T00:00:00</dataPronuntare><documentSedinta>incheieredesedinta</documentSedinta><numarDocument /><dataDocument>2019-01-11T00:00:00</dataDocument></DosarSedinta><DosarSedinta><complet>C13</complet><data>2018-11-12T00:00:00</data><ora>08:30</ora><solutie>Amână cauza</solutie><solutieSumar>- termen acordat pentru lipsa anchetei sociale de la domiciliul pârâtei şi a  răspunsului de la  Instituto Nazionale Previdenza Sociale Italia</solutieSumar><dataPronuntare xsi:nil="true" /><documentSedinta>incheieredesedinta</documentSedinta><numarDocument /><dataDocument>2018-11-12T00:00:00</dataDocument></DosarSedinta><DosarSedinta><complet>C13</complet><data>2018-10-01T00:00:00</data><ora>08:30</ora><solutie>Amână cauza</solutie><solutieSumar>Acordă termen pentru  a se reveni cu adresă la Instituto Nazionale Previdenza Sociale Italia.</solutieSumar><dataPronuntare xsi:nil="true" /><documentSedinta>incheieredesedinta</documentSedinta><numarDocument /><dataDocument>2018-10-01T00:00:00</dataDocument></DosarSedinta><DosarSedinta><complet>C13</complet><data>2018-09-05T00:00:00</data><ora>08:30</ora><solutie>Amână cauza</solutie><solutieSumar>Acordă termen pentru ca reclamanta să procedeze la traducerea anchetei întocmită de autorităţile italiene; pentru luarea interogatoriului pârâtei care a fost deja încuviinţat şi pentru a se reveni cu adresă la Instituto Nazionale Previdenza Sociale Italia.</solutieSumar><dataPronuntare xsi:nil="true" /><documentSedinta>incheieredesedinta</documentSedinta><numarDocument /><dataDocument>2018-09-05T00:00:00</dataDocument></DosarSedinta><DosarSedinta><complet>C13</complet><data>2018-06-27T00:00:00</data><ora>08:30</ora><solutie>Amână cauza</solutie><solutieSumar>Se va reveni cu adresă pentru efectuarea anchetei sociale dispusă în cauză.</solutieSumar><dataPronuntare xsi:nil="true" /><documentSedinta>incheieredesedinta</documentSedinta><numarDocument /><dataDocument>2018-06-27T00:00:00</dataDocument></DosarSedinta><DosarSedinta><complet>C13</complet><data>2018-05-07T00:00:00</data><ora>08:30</ora><solutie>Amână cauza</solutie><solutieSumar>lipsă anchetă socială şi relatii venituri</solutieSumar><dataPronuntare xsi:nil="true" /><documentSedinta>incheieredesedinta</documentSedinta><numarDocument /><dataDocument>2018-05-07T00:00:00</dataDocument></DosarSedinta><DosarSedinta><complet>C13</complet><data>2018-04-19T00:00:00</data><ora>08:30</ora><solutie>Amână cauza</solutie><solutieSumar>Pentru lipsa martorului,  a anchetei sociale şi audirea minorului. </solutieSumar><dataPronuntare>2018-04-19T00:00:00</dataPronuntare><documentSedinta>incheieredesedinta</documentSedinta><numarDocument /><dataDocument>2018-04-19T00:00:00</dataDocument></DosarSedinta><DosarSedinta><complet>C13</complet><data>2018-02-21T00:00:00</data><ora>08:30</ora><solutie>Amână cauza</solutie><solutieSumar>-	termen acordat pentru administrarea probelor solicitate de părţi</solutieSumar><dataPronuntare xsi:nil="true" /><documentSedinta>incheieredesedinta</documentSedinta><numarDocument /><dataDocument>2018-02-21T00:00:00</dataDocument></DosarSedinta><DosarSedinta><complet>C4</complet><data>2018-01-16T00:00:00</data><ora>08:30</ora><solutie>Amână cauza</solutie><solutieSumar>În vederea redistribuirii cauzei cf Hotărârii nr. 32/21.12.2017 a Colegiului de Conducere al Judecătoriei Botoşani.</solutieSumar><dataPronuntare>2018-01-16T00:00:00</dataPronuntare><documentSedinta>incheieredesedinta</documentSedinta><numarDocument /><dataDocument>2018-01-16T00:00:00</dataDocument></DosarSedinta></sedinte><caiAtac><DosarCaleAtac><dataDeclarare>2019-10-25T00:00:00</dataDeclarare><parteDeclaratoare> MOLDOVANU AURICA, </parteDeclaratoare><tipCaleAtac>Apel</tipCaleAtac></DosarCaleAtac><DosarCaleAtac><dataDeclarare>2019-09-12T00:00:00</dataDeclarare><parteDeclaratoare> MOLDOVANU AURICA, </parteDeclaratoare><tipCaleAtac>Apel</tipCaleAtac></DosarCaleAtac></caiAtac><numar>16983/193/2017</numar><numarVechi /><data>2017-09-22T13:14:00</data><institutie>JudecatoriaBOTOSANI</institutie><departament>Secţia Civilă</departament><categorieCaz>Minorisifamilie</categorieCaz><stadiuProcesual>Fond</stadiuProcesual><obiect>exercitarea autorităţii părinteşti</obiect><dataModificare>2019-11-20T16:23:20.787</dataModificare><categorieCazNume>Minori şi familie</categorieCazNume><stadiuProcesualNume>Fond</stadiuProcesualNume></Dosar><Dosar><parti><DosarParte><nume>ABABEI ELENA - MĂDĂLINA LA FAM BEREZOSCHI ALEXANDRINA</nume><calitateParte>Reclamant</calitateParte></DosarParte><DosarParte><nume>MIRIUŢĂ VASILE LA FAM MIRIUŢĂ IULICA</nume><calitateParte>Pârât</calitateParte></DosarParte></parti><sedinte><DosarSedinta><complet>C10</complet><data>2019-10-14T00:00:00</data><ora>09:00</ora><solutie>Alte soluţii</solutie><solutieSumar>Respinge cererea de chemare în judecată având ca obiect exercitare autoritate părintească, stabilire locuinţă, formulată de reclamanta -pârâta Ababei Elena-Mădălina, , în contradictoriu cu pârâtul-reclamant Miriuţă Vasile, , ca rămasă fără obiect.
Ia act că reclamanta-pârâtă a renunţat la capătul de cerere având ca obiect stabilire pensie de întreţinere.
	Admite cererea reconvenţională având ca obiect contestare recunoaştere paternitate, formulată de pârâtul-reclamant Miriuţă Vasile, în contradictoriu cu reclamanta -pârâta Ababei Elena-Mădălina, CNP .
	Constată că pârâtul-reclamant Miriuţă Vasile, , nu este tatăl minorei M. A.-M., născută la data de , CNP , în mun. Botoşani, jud. Botoşani, potrivit actului de naştere nr. 2273 din 08.10.2013, înregistrat la Muncipiul Botoşani, jud. Botoşani.
Dispune radierea numelui şi prenumelui pârâtului-reclamant Miriuţă Vasile din actul de naştere al minorei M. A.-M., născută la data de , de la rubrica „Tatăl”.
Minora M. A.-M., născută la data de , va purta, pe viitor, numele mamei de la data naşterii, acela de „ Berezoschi”.
Dispune modificarea menţiunilor din actul de naştere al minorei M. A.-M., născută la data de , urmând a se efectua cuvenitele modificări în registrul stării civile al Primăriei Botoşani jud. Botoşani.
Dispune ca exercitarea autorităţii părinteşti asupra minorei M. A.-M., născută la data de să fie efectuată de mamă, urmând ca aceasta să contribuie la întreţinerea minorului, prin asigurarea celor necesare traiului şi, după caz, a cheltuielilor pentru educare, învăţătură şi pregătire profesională.
Respinge cererea reclamantei-pârâte privind obligarea pârâtului-reclamant la plata cheltuielilor de judecată.
Executorie de drept cu privire exercitarea autorităţii părinteşti cu privire la minora M.A.-M..
Cu drept de apel in termen de 30 de zile de la comunicare, care se va depune la Judecătoria Botoşani.
	Pronun?ată prin punerea solu?iei la dispozi?ia păr?ilor prin mijlocire grefei instanţei azi, 14.10.2019.

</solutieSumar><dataPronuntare>2019-10-14T00:00:00</dataPronuntare><documentSedinta>Hotarare</documentSedinta><numarDocument>4052/2019</numarDocument><dataDocument>2019-10-14T00:00:00</dataDocument></DosarSedinta><DosarSedinta><complet>C10</complet><data>2019-10-09T00:00:00</data><ora>08:30</ora><solutie>Amână pronunţarea</solutie><solutieSumar>Amână pronunţarea la data de 14.10.2019, pentru când pronunţarea se va face prin punerea soluţiei la dispoziţia părţilor prin mijlocirea grefei instanţei. 
Pronunţată prin punerea soluţiei la dispoziţia instanţei prin mijlocirea grefei instanţei, 09.10.2019.

</solutieSumar><dataPronuntare>2019-10-09T00:00:00</dataPronuntare><documentSedinta>incheiereAmanareinitialaapronuntarii</documentSedinta><numarDocument /><dataDocument>2019-10-09T00:00:00</dataDocument></DosarSedinta><DosarSedinta><complet>C10</complet><data>2019-06-26T00:00:00</data><ora>08:30</ora><solutie>Amână cauza</solutie><solutieSumar>Repune cauza pe rol.
Se va reveni cu adresa catre IML pentru a intocmi raportul de expertiza medico-legal, examen ADN.</solutieSumar><dataPronuntare>2019-06-26T00:00:00</dataPronuntare><documentSedinta>incheieredesedinta</documentSedinta><numarDocument /><dataDocument>2019-06-26T00:00:00</dataDocument></DosarSedinta><DosarSedinta><complet>C10</complet><data>2019-03-27T00:00:00</data><ora>08:30</ora><solutie>411 NCPC/242 CPC</solutie><solutieSumar> În temeiul disp. art. 411 alin. (1) pct. 1 Cod de procedură civilă, suspendă judecata cererii de chemare în judecată, având ca obiect exercitare autoritate părintească formulată de reclamanta-pârât Ababei Elena-Mădălina în contradictoriu cu pârâtul-reclamant  Berezoschi Alexandrina.
Cu drept de recurs pe durata suspendării, care se depune la Judecătoria Botoşani.
Pronunţată în şedinţă publică azi,  27.03.2019.
</solutieSumar><dataPronuntare>2019-03-27T00:00:00</dataPronuntare><documentSedinta>incheiereSuspendare</documentSedinta><numarDocument /><dataDocument>2019-03-27T00:00:00</dataDocument></DosarSedinta><DosarSedinta><complet>C10</complet><data>2019-02-21T00:00:00</data><ora>08:30</ora><solutie>Amână cauza</solutie><solutieSumar>În vederea administrării probei cu martori</solutieSumar><dataPronuntare>2019-02-21T00:00:00</dataPronuntare><documentSedinta>incheieredesedinta</documentSedinta><numarDocument /><dataDocument>2019-02-21T00:00:00</dataDocument></DosarSedinta><DosarSedinta><complet>C10</complet><data>2019-01-08T00:00:00</data><ora>08:30</ora><solutie>Amână cauza</solutie><solutieSumar>Repune cauza pe rol.
Acorda termen pentru a se reveni cu adresă către IML Iaşi pentru efectuarea expertizei serologice.</solutieSumar><dataPronuntare>2019-01-08T00:00:00</dataPronuntare><documentSedinta>incheieredesedinta</documentSedinta><numarDocument /><dataDocument>2019-01-08T00:00:00</dataDocument></DosarSedinta><DosarSedinta><complet>C10</complet><data>2018-09-04T00:00:00</data><ora>08:30</ora><solutie>Amână cauza</solutie><solutieSumar> În temeiul disp. art. 242 alin. 2  Cod de procedură civilă, suspendă judecata cererii de chemare în judecată, având ca obiect exercitare autoritate părintească, formulată de reclamanta Ababei Elena-Madalina în contradictoriu cu pârâtul Miriuţă Vasile. 
Cu drept de recurs pe durata suspendării, care se depune la Judecătoria Botoşani.
Pronunţată în şedinţă publică azi,  04.09.2018.
</solutieSumar><dataPronuntare>2018-09-04T00:00:00</dataPronuntare><documentSedinta>incheiereSuspendare</documentSedinta><numarDocument /><dataDocument>2018-09-04T00:00:00</dataDocument></DosarSedinta><DosarSedinta><complet>C10</complet><data>2018-05-30T00:00:00</data><ora>08:30</ora><solutie>Amână cauza</solutie><solutieSumar>pentru efectuarea expertizei serologice şi administrarea probei cu martorii încuviinţaţi</solutieSumar><dataPronuntare>2018-05-30T00:00:00</dataPronuntare><documentSedinta>incheieredesedinta</documentSedinta><numarDocument /><dataDocument>2018-05-30T00:00:00</dataDocument></DosarSedinta><DosarSedinta><complet>C10</complet><data>2018-03-29T00:00:00</data><ora>08:30</ora><solutie>Amână cauza</solutie><solutieSumar>Acordă termen pentru administrarea probei cu expertiza medico-legală, examen ADN.
</solutieSumar><dataPronuntare>2018-03-29T00:00:00</dataPronuntare><documentSedinta>incheieredesedinta</documentSedinta><numarDocument /><dataDocument>2018-03-29T00:00:00</dataDocument></DosarSedinta><DosarSedinta><complet>C10</complet><data>2018-01-19T00:00:00</data><ora>08:30</ora><solutie>Amână cauza</solutie><solutieSumar>Amână cauza în vedere administrării probatoriului încuviinţat.
Pune în vedere părţilor să asigure prezenţa martorilor.</solutieSumar><dataPronuntare>2018-01-19T00:00:00</dataPronuntare><documentSedinta>incheieredesedinta</documentSedinta><numarDocument /><dataDocument>2018-01-19T00:00:00</dataDocument></DosarSedinta></sedinte><numar>19294/193/2017</numar><numarVechi /><data>2017-10-25T09:44:00</data><institutie>JudecatoriaBOTOSANI</institutie><departament>Secţia Civilă</departament><categorieCaz>Minorisifamilie</categorieCaz><stadiuProcesual>Fond</stadiuProcesual><obiect>exercitarea autorităţii părinteşti</obiect><dataModificare>2019-12-04T18:01:03.467</dataModificare><categorieCazNume>Minori şi familie</categorieCazNume><stadiuProcesualNume>Fond</stadiuProcesualNume></Dosar><Dosar><parti><DosarParte><nume>ŞUIU ANA - CLAUDIA</nume><calitateParte>Reclamant</calitateParte></DosarParte><DosarParte><nume>BOTOŞINEANU DUMITRU</nume><calitateParte>Pârât</calitateParte></DosarParte></parti><sedinte><DosarSedinta><complet>C21</complet><data>2018-06-25T00:00:00</data><ora>08:30</ora><solutie>Admite in parte cererea</solutie><solutieSumar>Admite în parte acţiunea având ca obiect măsuri privind minorul formulată de reclamanta  Şuiu Ana Claudia în contradictoriu cu pârâtul Botoşineanu Dumitru.
	Dispune ca autoritatea părintească asupra minorului Botoşineanu Ianis Andrei născut la data de 17.03.2017, să fie exercitată în comun de către ambii părinţi.
	Menţine obligaţia de plată a pensiei de întreţinere stabilită prin Sentinţa civilă nr. 9321/08.12.2016 pronunţată de Judecătoria Botoşani în dosarul nr. 6968/193/2016 şi în consecinţă dispune în sarcina pârâtului,  achitarea către mama minorului a unei pensii de întreţinere pentru minorul Botoşineanu Ianis Andrei născut la data de 17.03.2017, în cuantum de 300 lei/ lună, începând cu data introducerii acţiunii, respectiv 17.11.2017 până la majoratul minorului.
Obligă reclamanta să plătească pârâtului suma de 300 lei, cu titlu de cheltuieli de judecată, reprezentând onorariu avocat.
	Cu drept de apel în 30 de zile de la comunicare, care se depune la Judecătoria Botoşani.
	Pronunţată în şedinţă publică, azi, 25.06.2018.

</solutieSumar><dataPronuntare>2018-06-25T00:00:00</dataPronuntare><documentSedinta>Hotarare</documentSedinta><numarDocument>2971/2018</numarDocument><dataDocument>2018-06-25T00:00:00</dataDocument></DosarSedinta><DosarSedinta><complet>C21</complet><data>2018-05-30T00:00:00</data><ora>08:30</ora><solutie>Amână cauza</solutie><solutieSumar>Amână cauza în vederea prezentării avocatului titular.</solutieSumar><dataPronuntare>2018-05-30T00:00:00</dataPronuntare><documentSedinta>incheieredesedinta</documentSedinta><numarDocument /><dataDocument>2018-05-30T00:00:00</dataDocument></DosarSedinta><DosarSedinta><complet>C21</complet><data>2018-05-03T00:00:00</data><ora>08:30</ora><solutie>Amână cauza</solutie><solutieSumar>Amână cauza în vederea continuării cercetării judecătoreşti.</solutieSumar><dataPronuntare>2018-05-03T00:00:00</dataPronuntare><documentSedinta>incheieredesedinta</documentSedinta><numarDocument /><dataDocument>2018-05-03T00:00:00</dataDocument></DosarSedinta><DosarSedinta><complet>C21</complet><data>2018-03-21T00:00:00</data><ora>08:30</ora><solutie>Amână cauza</solutie><solutieSumar>Amână cauza în vederea continuării cercetării judecătoreşti.</solutieSumar><dataPronuntare>2018-03-21T00:00:00</dataPronuntare><documentSedinta>incheieredesedinta</documentSedinta><numarDocument /><dataDocument>2018-03-21T00:00:00</dataDocument></DosarSedinta><DosarSedinta><complet>C21</complet><data>2018-02-15T00:00:00</data><ora>08:30</ora><solutie>Amână cauza</solutie><solutieSumar>Amână cauza în vederea continuării cercetării judecătoreşti.</solutieSumar><dataPronuntare>2018-02-15T00:00:00</dataPronuntare><documentSedinta>incheieredesedinta</documentSedinta><numarDocument /><dataDocument>2018-02-15T00:00:00</dataDocument></DosarSedinta></sedinte><caiAtac><DosarCaleAtac><dataDeclarare>2018-08-21T00:00:00</dataDeclarare><parteDeclaratoare> ŞUIU ANA - CLAUDIA, </parteDeclaratoare><tipCaleAtac>Apel</tipCaleAtac></DosarCaleAtac></caiAtac><numar>21052/193/2017</numar><numarVechi /><data>2017-11-17T11:33:00</data><institutie>JudecatoriaBOTOSANI</institutie><departament>Secţia Civilă</departament><categorieCaz>Minorisifamilie</categorieCaz><stadiuProcesual>Fond</stadiuProcesual><obiect>exercitarea autorităţii părinteşti</obiect><dataModificare>2018-08-31T17:26:16.313</dataModificare><categorieCazNume>Minori şi familie</categorieCazNume><stadiuProcesualNume>Fond</stadiuProcesualNume></Dosar><Dosar><parti><DosarParte><nume>GRĂDINARU MARIANA</nume><calitateParte>Reclamant</calitateParte></DosarParte><DosarParte><nume>GRĂDINARU GABRIEL - GELU</nume><calitateParte>Pârât</calitateParte></DosarParte></parti><sedinte><DosarSedinta><complet>C7</complet><data>2018-06-13T00:00:00</data><ora>08:30</ora><solutie>Respinge cererea</solutie><solutieSumar>Respinge cererea de exercitare exclusivă a autorităţii părinteşti formulată de reclamanta Grădinaru Mariana în contradictoriu cu pârâtul Grădinaru Gabriel – Gelu, ca neîntemeiată.
	Respinge capătul de cerere privind acordarea cheltuielilor de judecată, ca neîntemeiat.	
Cu drept de apel în termen de 30 de zile de la comunicare, cererea şi motivele de apel urmând a se depune la Judecătoria Botoşani.
Pronunţată în şedinţă publică, astăzi, 13.06.2018.
</solutieSumar><dataPronuntare>2018-06-13T00:00:00</dataPronuntare><documentSedinta>Hotarare</documentSedinta><numarDocument>2740/2018</numarDocument><dataDocument>2018-06-13T00:00:00</dataDocument></DosarSedinta><DosarSedinta><complet>C7</complet><data>2018-05-17T00:00:00</data><ora>08:30</ora><solutie>Amână cauza</solutie><solutieSumar>acorda un nou termen de judecată pentru a se lua la cunoştinţă de raportul orivind copiii, întocmit de Direcţia pentru Protecţia Copilului Botoşani</solutieSumar><dataPronuntare xsi:nil="true" /><documentSedinta>incheieredesedinta</documentSedinta><numarDocument /><dataDocument>2018-05-17T00:00:00</dataDocument></DosarSedinta><DosarSedinta><complet>C7</complet><data>2018-04-12T00:00:00</data><ora>08:30</ora><solutie>Amână cauza</solutie><solutieSumar>Încuviinţează efectuarea unui raport privind minorele  Grădinaru Gabriela Simina  - născută la data de 06.10.2012 şi Grădinaru Mihaela Denisa, născută la data de 06.10.2012, pentru a se stabili natura relaţiei cu ambii părinţi şi apropierea copiilor faţă de aceştia, în conformitate cu disp. art. 139 din Legea nr. 272/2004, republicată.</solutieSumar><dataPronuntare xsi:nil="true" /><documentSedinta>incheieredesedinta</documentSedinta><numarDocument /><dataDocument>2018-04-12T00:00:00</dataDocument></DosarSedinta><DosarSedinta><complet>C7</complet><data>2018-03-08T00:00:00</data><ora>08:30</ora><solutie>Amână cauza</solutie><solutieSumar>Încuviinţează probatoriul solicitat de părţi, cu înscrisuri, martori şi interogatoriu civil pârâtului, sens în care acesta urmează a fi citat cu menţiunea de a se prezenta “personal la interogatoriu”. 
Prorogă proba privind evaluarea psihologică a minorilor după ascultarea pârâtului, dacă va aprecia necesar.
</solutieSumar><dataPronuntare xsi:nil="true" /><documentSedinta>incheieredesedinta</documentSedinta><numarDocument /><dataDocument>2018-03-08T00:00:00</dataDocument></DosarSedinta><DosarSedinta><complet>C7</complet><data>2018-01-26T00:00:00</data><ora>08:30</ora><solutie>Amână cauza</solutie><solutieSumar>Având în vedere lipsa reclamantei şi a apărătorului acesteia, în raport de probele propuse dar şi de apărările formulate pentru pârât, va dispune amânarea cauzei şi acordarea unui termen de judecată pentru asigurarea continuităţii completului legal învestit cu soluţionarea cauzei.</solutieSumar><dataPronuntare xsi:nil="true" /><documentSedinta>incheieredesedinta</documentSedinta><numarDocument /><dataDocument>2018-01-26T00:00:00</dataDocument></DosarSedinta></sedinte><caiAtac><DosarCaleAtac><dataDeclarare>2018-08-07T00:00:00</dataDeclarare><parteDeclaratoare> GRĂDINARU MARIANA, </parteDeclaratoare><tipCaleAtac>Apel</tipCaleAtac></DosarCaleAtac></caiAtac><numar>21114/193/2017</numar><numarVechi /><data>2017-11-20T11:54:00</data><institutie>JudecatoriaBOTOSANI</institutie><departament>Secţia Civilă</departament><categorieCaz>Minorisifamilie</categorieCaz><stadiuProcesual>Fond</stadiuProcesual><obiect>exercitarea autorităţii părinteşti</obiect><dataModificare>2018-08-21T17:31:31.25</dataModificare><categorieCazNume>Minori şi familie</categorieCazNume><stadiuProcesualNume>Fond</stadiuProcesualNume></Dosar><Dosar><parti><DosarParte><nume>TÎRNAUCĂ GEANINA</nume><calitateParte>Reclamant</calitateParte></DosarParte><DosarParte><nume>IGNĂTOAIE IONEL</nume><calitateParte>Pârât</calitateParte></DosarParte><DosarParte><nume>IGNĂTOAIE IONEL la SC CALDO PRIVAT SECURITY SRL</nume><calitateParte>Pârât</calitateParte></DosarParte></parti><sedinte><DosarSedinta><complet>C7</complet><data>2018-05-17T00:00:00</data><ora>08:30</ora><solutie>Admite cererea</solutie><solutieSumar>Admite cererea de stabilire a autorităţii părinteşti + accesorii formulată de reclamanta Tîrnaucă Geanina în contradictoriu cu pârâtul Ignătoaie Ionel.
	Dispune exercitarea în comun de către ambii părinţi a autorităţii părinteşti asupra minorei Ignătoaie Ioana – Liliana.
	Stabileşte locuinţa minorei la domiciliul mamei reclamante.
	Dispune ca pârâtul să achite către mama reclamantă o pensie de întreţinere pentru minora Ignătoaie Ioana – Liliana, în cuantum de 290 lei / lună, începând cu data formulării cererii (21.11.2017) şi până la majoratul acesteia.
Obligă pârâtul la plata către reclamantă a sumei de 250 de lei cu titlu de cheltuieli de judecată, reprezentând jumătate din onorariul de avocat achitat de aceasta.
Cu drept de apel în termen de 30 de zile de la comunicare, cererea şi motivele de apel urmând a se depune la Judecătoria Botoşani.
Pronunţată în şedinţă publică, astăzi, 17.05.2018.
</solutieSumar><dataPronuntare>2018-05-17T00:00:00</dataPronuntare><documentSedinta>Hotarare</documentSedinta><numarDocument>2229/2018</numarDocument><dataDocument>2018-05-17T00:00:00</dataDocument></DosarSedinta><DosarSedinta><complet>C7</complet><data>2018-04-20T00:00:00</data><ora>08:30</ora><solutie>Amână cauza</solutie><solutieSumar>pentru citarea paratului personal la interogatoriu</solutieSumar><dataPronuntare xsi:nil="true" /><documentSedinta>incheieredesedinta</documentSedinta><numarDocument /><dataDocument>2018-04-20T00:00:00</dataDocument></DosarSedinta><DosarSedinta><complet>C7</complet><data>2018-03-08T00:00:00</data><ora>08:30</ora><solutie>Amână cauza</solutie><solutieSumar>Dispune a se relua procedura de citare cu pârâtul, cu menţiunea de a se prezenta “personal la interogatoriu”,  la toate adresele indicate.
Dispune emiterea unor adrese către ITM Botoşani şi AJFP Botoşani pentru a se solicita relaţii privind locul de muncă al pârâtului, denumirea şi sediul angajatorului, precum şi veniturile realizate. 
Dispune emiterea unei adrese către autoritatea tutelară din cadrul Primăriei Botoşani pentru a proceda la întocmirea unui referat de anchetă socială la domiciliul reclamantei.
În temeiul art. 229 Cod pr. Civilă, reclamanta primeşte termen în cunoştinţă prin apărător
</solutieSumar><dataPronuntare xsi:nil="true" /><documentSedinta>incheieredesedinta</documentSedinta><numarDocument /><dataDocument>2018-03-08T00:00:00</dataDocument></DosarSedinta><DosarSedinta><complet>C7</complet><data>2018-02-02T00:00:00</data><ora>08:30</ora><solutie>Amână cauza</solutie><solutieSumar>pentru lipsa de procedură cu pârâtul va dispune amânarea cauzei</solutieSumar><dataPronuntare xsi:nil="true" /><documentSedinta>incheieredesedinta</documentSedinta><numarDocument /><dataDocument>2018-02-02T00:00:00</dataDocument></DosarSedinta></sedinte><caiAtac><DosarCaleAtac><dataDeclarare>2018-06-13T00:00:00</dataDeclarare><parteDeclaratoare> IGNĂTOAIE IONEL, </parteDeclaratoare><tipCaleAtac>Apel</tipCaleAtac></DosarCaleAtac></caiAtac><numar>21250/193/2017</numar><numarVechi /><data>2017-11-21T12:18:00</data><institutie>JudecatoriaBOTOSANI</institutie><departament>Secţia Civilă</departament><categorieCaz>Minorisifamilie</categorieCaz><stadiuProcesual>Fond</stadiuProcesual><obiect>exercitarea autorităţii părinteşti</obiect><dataModificare>2018-07-18T17:43:51.74</dataModificare><categorieCazNume>Minori şi familie</categorieCazNume><stadiuProcesualNume>Fond</stadiuProcesualNume></Dosar><Dosar><parti><DosarParte><nume>RADU (FOSTĂ LOCIC) OANA</nume><calitateParte>Reclamant</calitateParte></DosarParte><DosarParte><nume>IORDĂCHESCU MARIUS - AURELIAN</nume><calitateParte>Pârât</calitateParte></DosarParte><DosarParte><nume>IORDĂCHESCU MARIUS - AURELIAN-CU DOMICILIUL PROCESUAL ALES LA</nume><calitateParte>Pârât</calitateParte></DosarParte></parti><sedinte><DosarSedinta><complet>C13</complet><data>2018-09-25T00:00:00</data><ora>08:30</ora><solutie>Admite in parte cererea</solutie><solutieSumar>Admite în parte acţiunea formulată de reclamanta-pârâtă RADU Oana (fostă Locic),  în contradictoriu cu pârâtul-reclamant IORDĂCHESCU Marius-Aurelian.
Admite cererea reconvenţională formulată de pârâtul reclamant IORDĂCHESCU Marius-Aurelian.
Dispune ca autoritatea părintească asupra minorului I.D.M. ordăchescu  să fie exercitată în comun de către ambii părinţi I.D.M. David-Marius, la domiciliul tatălui. 
Stabileşte programul pentru legături personale al reclamantei-pârâte cu fiul său I.D.M.astfel: 
-	primul şi al treilea week-end din lună, începând cu orele 10:00 până la orele 16:00, doua zi de Paşte, a doua zi de Crăciun, 3 zile în vacanţa de iarnă, la domiciliul pârâtului sau în alt loc public;
Obligă reclamanta-pârâtă să plătească în favoarea minorului IDM  cu titlu de pensie de întreţinere suma de 160 de lei lunar începând cu data introducerii cererii, respectiv 14.02.2018 şi până la majoratul copilului sau până la intervenirea unei alte cauze de încetare a obligaţiei de întreţinere.
Ia act că nu s-au solicitat cheltuieli judiciare.
Executorie.
Cu apel în 30 de zile de la comunicare care se depune la Judecătoria Botoşani.
Pronunţată prin punerea soluţiei la dispoziţia părţilor prin mijlocirea grefei instanţei în data de 25.09.2018.

</solutieSumar><dataPronuntare>2018-09-25T00:00:00</dataPronuntare><documentSedinta>Hotarare</documentSedinta><numarDocument>3924/2018</numarDocument><dataDocument>2018-09-25T00:00:00</dataDocument></DosarSedinta><DosarSedinta><complet>C13</complet><data>2018-09-13T00:00:00</data><ora>08:30</ora><solutie>Amână pronunţarea</solutie><solutieSumar>Amână pronunţarea la data de 25.09.2018, pronunţarea urmând a se face prin punerea soluţiei la dispoziţia părţilor prin mijlocirea grefei instanţei.
Pronunţată în şedinţă publică, azi, data de 13.09.2018.


</solutieSumar><dataPronuntare xsi:nil="true" /><documentSedinta>incheiereAmanareinitialaapronuntarii</documentSedinta><numarDocument /><dataDocument>2018-09-13T00:00:00</dataDocument></DosarSedinta><DosarSedinta><complet>C13</complet><data>2018-06-11T00:00:00</data><ora>08:30</ora><solutie>Amână cauza</solutie><solutieSumar>Pentru a fi citaţi martorii reclamantei şi audierea martorilor la acelaşi termen. </solutieSumar><dataPronuntare>2018-06-11T00:00:00</dataPronuntare><documentSedinta>incheieredesedinta</documentSedinta><numarDocument /><dataDocument>2018-06-11T00:00:00</dataDocument></DosarSedinta><DosarSedinta><complet>C13</complet><data>2018-05-07T00:00:00</data><ora>08:30</ora><solutie>Amână cauza</solutie><solutieSumar>lipsă martori</solutieSumar><dataPronuntare xsi:nil="true" /><documentSedinta>incheieredesedinta</documentSedinta><numarDocument /><dataDocument>2018-05-07T00:00:00</dataDocument></DosarSedinta><DosarSedinta><complet>C13</complet><data>2018-04-19T00:00:00</data><ora>08:30</ora><solutie>Amână cauza</solutie><solutieSumar>Pentru administrarea probatoriului încuviinţat.</solutieSumar><dataPronuntare>2018-04-19T00:00:00</dataPronuntare><documentSedinta>incheieredesedinta</documentSedinta><numarDocument /><dataDocument>2018-04-19T00:00:00</dataDocument></DosarSedinta><DosarSedinta><complet>C13</complet><data>2018-03-19T00:00:00</data><ora>08:30</ora><solutie>Amână cauza</solutie><solutieSumar>termen acordat reclamantei pentru apărare </solutieSumar><dataPronuntare xsi:nil="true" /><documentSedinta>incheieredesedinta</documentSedinta><numarDocument /><dataDocument>2018-03-19T00:00:00</dataDocument></DosarSedinta></sedinte><numar>22779/193/2017</numar><numarVechi /><data>2017-12-15T11:19:00</data><institutie>JudecatoriaBOTOSANI</institutie><departament>Secţia Civilă</departament><categorieCaz>Minorisifamilie</categorieCaz><stadiuProcesual>Fond</stadiuProcesual><obiect>exercitarea autorităţii părinteşti</obiect><dataModificare>2018-12-23T21:42:09.827</dataModificare><categorieCazNume>Minori şi familie</categorieCazNume><stadiuProcesualNume>Fond</stadiuProcesualNume></Dosar><Dosar><parti><DosarParte><nume>LĂŢEA DUMITRU</nume><calitateParte>Reclamant</calitateParte></DosarParte><DosarParte><nume>POPOVICI ANGELA</nume><calitateParte>Reclamant</calitateParte></DosarParte><DosarParte><nume>VACARU (FOSTĂ LĂŢEA) ELENA</nume><calitateParte>Pârât</calitateParte></DosarParte></parti><sedinte><DosarSedinta><complet>C11</complet><data>2018-09-21T00:00:00</data><ora>08:30</ora><solutie>Admite cererea</solutie><solutieSumar>Admite acţiunea formulată de reclamanţii Lăţea Dumitru şi Popovici Angela în contradictoriu cu pârâta Vacaru (fostă Lăţea) Elena având ca obiect „exercitare autoritate părintească”.
Dispune ca exercitarea autorităţii părinteşti asupra minorei Lăţea Maria, născută la data de 03.11.2004, să se realizeze exclusiv de către tată,  reclamantul Lăţea Dumitru
Stabileşte domiciliul minorei Lăţea Maria, născută la data de 03.11.2004, la domiciliul bunicii, respectiv reclamanta  Popovici Angela.
Stabileşte în sarcina  pârâtei Vacaru (fostă Lăţea) Elena obligaţia de întreţinere, în bani, în favoarea minorei Lăţea Maria, născută la data de 03.11.2004, în cuantum de 290,05 lei lunar, cu începere de la data introducerii prezentei acţiuni, respectiv 19.12.2017, şi până la majoratul acesteia.
Cu drept de apel în termen de 30 zile de la comunicare.
Cererea de apel se depune la Judecătoria Botoşani.
Pronunţarea hotărârii se va face prin punerea soluţiei la dispoziţia părţilor prin mijlocirea grefei instanţei, la data de 21.09.2018.

</solutieSumar><dataPronuntare>2018-09-21T00:00:00</dataPronuntare><documentSedinta>Hotarare</documentSedinta><numarDocument>3820/2018</numarDocument><dataDocument>2018-09-21T00:00:00</dataDocument></DosarSedinta><DosarSedinta><complet>C11</complet><data>2018-09-07T00:00:00</data><ora>08:30</ora><solutie>Amână cauza</solutie><solutieSumar>Amână pronunţarea la data de 21.09.2018, pronunţarea urmând a se face prin punerea soluţiei la dispoziţia părţilor prin mijlocirea grefei instanţei.
Pronunţată în şedinţă publică azi, 07.09.2018.</solutieSumar><dataPronuntare>2018-09-07T00:00:00</dataPronuntare><documentSedinta>incheiereAmanareinitialaapronuntarii</documentSedinta><numarDocument /><dataDocument>2018-09-07T00:00:00</dataDocument></DosarSedinta><DosarSedinta><complet>C11</complet><data>2018-06-20T00:00:00</data><ora>08:30</ora><solutie>Amână cauza</solutie><solutieSumar>Revenire citare pârât. </solutieSumar><dataPronuntare>2018-06-20T00:00:00</dataPronuntare><documentSedinta>incheieredesedinta</documentSedinta><numarDocument /><dataDocument>2018-06-20T00:00:00</dataDocument></DosarSedinta><DosarSedinta><complet>C11</complet><data>2018-05-24T00:00:00</data><ora>08:30</ora><solutie>Amână cauza</solutie><solutieSumar>pentru audiere martor</solutieSumar><dataPronuntare>2018-05-24T00:00:00</dataPronuntare><documentSedinta>incheieredesedinta</documentSedinta><numarDocument /><dataDocument>2018-05-24T00:00:00</dataDocument></DosarSedinta><DosarSedinta><complet>C11</complet><data>2018-04-13T00:00:00</data><ora>08:30</ora><solutie>Amână cauza</solutie><solutieSumar>Se acordă un nou termen pentru administrarea probelor propuse.</solutieSumar><dataPronuntare xsi:nil="true" /><documentSedinta>incheieredesedinta</documentSedinta><numarDocument /><dataDocument>2018-04-13T00:00:00</dataDocument></DosarSedinta></sedinte><numar>22883/193/2017</numar><numarVechi /><data>2017-12-19T10:22:00</data><institutie>JudecatoriaBOTOSANI</institutie><departament>Secţia Civilă</departament><categorieCaz>Minorisifamilie</categorieCaz><stadiuProcesual>Fond</stadiuProcesual><obiect>exercitarea autorităţii părinteşti</obiect><dataModificare>2018-09-29T13:34:10.563</dataModificare><categorieCazNume>Minori şi familie</categorieCazNume><stadiuProcesualNume>Fond</stadiuProcesualNume></Dosar></CautareDosareResult></CautareDosareResponse></soap:Body></soap:Envelope>